table_file_parser/ReadAndSplit_Chunk.py
table_file_parser/__init__.py
table_file_parser/dataLoader/__init__.py
table_file_parser/dataLoader/base_file_loader.py
table_file_parser/dataLoader/excel_loader.py
table_file_parser/dataLoader/file_loader_factory.py
table_file_parser/dataLoader/hdf5_loader.py
table_file_parser/dataLoader/single_table_loader.py
table_file_parser/dataWriter/__init__.py
table_file_parser/dataWriter/base_writer_utils.py
table_file_parser/dataWriter/parquet_writer.py
table_file_parser/dataWriter/pyarrow_writer.py
table_file_parser/duckDBUtils/__init__.py
table_file_parser/duckDBUtils/my_parquet_fts_indexer_upgrade.py
table_file_parser/huggingface/__init__.py
table_file_parser/huggingface/my_huggingface_descriptive_statistics.py
table_file_parser/utils/FileLogger.py
table_file_parser/utils/Invaild_Chars.py
table_file_parser/utils/__init__.py
table_file_parser/utils/arrow_reader.py
table_file_parser/utils/csv_chunk_read_util.py
table_file_parser/utils/header_detector.py
table_file_parser/utils/my_pandas_type_confirming_utils.py
table_file_parser/utils/sciencedb_output_info_generator.py
table_file_parser/utils/split_file_name_format_checker.py
table_file_parser/utils/tab_chunk_read_util.py
table_file_parser/utils/thread_util.py
table_file_parser-0.1.5.dist-info/METADATA
table_file_parser-0.1.5.dist-info/WHEEL
table_file_parser-0.1.5.dist-info/top_level.txt
table_file_parser-0.1.5.dist-info/RECORD
